Metadata-Version: 1.0
Name: stati-probability
Version: 1.0
Summary: Gaussian distributions
Home-page: https://github.com/hanyhabs
Author: Hany
Author-email: hanybs98@gmail.com
License: MIT
Platform: any
